{
  "Workflows": [
    {
      "Path": null,
      "SortBy": 0,
      "VariablesSectionElementsOrder": [],
      "ArgumentsSectionElementsOrder": null,
      "ConstantsSectionElementsOrder": [],
      "AddedNamespaces": null
    },
    {
      "Path": "ExceptionManagement.xaml",
      "SortBy": 0,
      "VariablesSectionElementsOrder": [
        "Config&Sequence_1",
        "str_WF_ErrorMessageToRpaTeam&Sequence_1",
        "str_WF_ErrorMessageToBusiness&Sequence_1",
        "bool_CheckFlow&Sequence_1"
      ],
      "ArgumentsSectionElementsOrder": [],
      "ConstantsSectionElementsOrder": [],
      "AddedNamespaces": null
    },
    {
      "Path": "Main_TemplateWorkflow.xaml",
      "SortBy": 0,
      "VariablesSectionElementsOrder": [],
      "ArgumentsSectionElementsOrder": [
        "io_str_WF_ErrorMessageToRpaTeam",
        "io_str_WF_ErrorMessageToBusiness",
        "io_bool_CheckFlow"
      ],
      "ConstantsSectionElementsOrder": [],
      "AddedNamespaces": null
    }
  ]
}