{
  "Workflows": [
    {
      "Path": null,
      "SortBy": 0,
      "VariablesSectionElementsOrder": [],
      "ArgumentsSectionElementsOrder": null,
      "ConstantsSectionElementsOrder": [],
      "AddedNamespaces": null
    },
    {
      "Path": "CreateNewQueue.xaml",
      "SortBy": 0,
      "VariablesSectionElementsOrder": [],
      "ArgumentsSectionElementsOrder": [
        "in_str_QueueName",
        "in_str_QueueDescription",
        "in_str_QueueRetryNumber"
      ],
      "ConstantsSectionElementsOrder": [],
      "AddedNamespaces": null
    }
  ]
}